hooks.py
pchanial_legacy_install_hooks-1.6.dist-info/LICENCE_FR
pchanial_legacy_install_hooks-1.6.dist-info/LICENSE
pchanial_legacy_install_hooks-1.6.dist-info/METADATA
pchanial_legacy_install_hooks-1.6.dist-info/WHEEL
pchanial_legacy_install_hooks-1.6.dist-info/top_level.txt
pchanial_legacy_install_hooks-1.6.dist-info/RECORD
